spiderexpress/__init__.py
spiderexpress/cli.py
spiderexpress/connectors/__init__.py
spiderexpress/connectors/csv.py
spiderexpress/model.py
spiderexpress/plugin_manager.py
spiderexpress/router.py
spiderexpress/spider.py
spiderexpress/strategies/__init__.py
spiderexpress/strategies/random.py
spiderexpress/strategies/snowball.py
spiderexpress/strategies/spikyball.py
spiderexpress/types.py
spiderexpress-0.2.0a0.dist-info/LICENSE
spiderexpress-0.2.0a0.dist-info/METADATA
spiderexpress-0.2.0a0.dist-info/WHEEL
spiderexpress-0.2.0a0.dist-info/entry_points.txt
spiderexpress-0.2.0a0.dist-info/RECORD
