Metadata-Version: 2.1
Name: spiderexpress
Version: 0.2.0a0
Summary: A multipurpose spidery crawler for social media platforms
License: MIT
Author: Philipp Kessling
Author-email: p.kessling@leibniz-hbi.de
Requires-Python: >=3.10,<4.0
Classifier: License :: OSI Approved :: MIT License
Classifier: Programming Language :: Python :: 3
Classifier: Programming Language :: Python :: 3.10
Classifier: Programming Language :: Python :: 3.11
Classifier: Programming Language :: Python :: 3.12
Classifier: Programming Language :: Python :: 3.13
Requires-Dist: PyYAML
Requires-Dist: SQLAlchemy
Requires-Dist: click
Requires-Dist: loguru
Requires-Dist: numpy
Requires-Dist: pandas
Requires-Dist: psycopg2-binary
Requires-Dist: pydantic (>=2.9.2,<3.0.0)
Requires-Dist: transitions
